webanalyzer/__init__.py
webanalyzer/Checking/__init__.py
webanalyzer/Checking/test.py
webanalyzer_api-1.0.dist-info/LICENSE.txt
webanalyzer_api-1.0.dist-info/METADATA
webanalyzer_api-1.0.dist-info/WHEEL
webanalyzer_api-1.0.dist-info/top_level.txt
webanalyzer_api-1.0.dist-info/RECORD
